xmlhelpy/__init__.py
xmlhelpy/core.py
xmlhelpy/decorators.py
xmlhelpy/formatting.py
xmlhelpy/types.py
xmlhelpy-0.14.0.dist-info/LICENSE
xmlhelpy-0.14.0.dist-info/METADATA
xmlhelpy-0.14.0.dist-info/WHEEL
xmlhelpy-0.14.0.dist-info/top_level.txt
xmlhelpy-0.14.0.dist-info/RECORD
