Metadata-Version: 2.1
Name: xmlhelpy
Version: 0.14.0
Summary: CLI wrapper supporting the xmlhelp interface.
Author: Karlsruhe Institute of Technology
License: Apache-2.0
Project-URL: Source, https://gitlab.com/iam-cms/workflows/xmlhelpy
Classifier: Development Status :: 4 - Beta
Classifier: License :: OSI Approved :: Apache Software License
Classifier: Operating System :: OS Independent
Classifier: Programming Language :: Python :: 3
Requires-Python: <3.14,>=3.9
License-File: LICENSE
Requires-Dist: click <9.0.0,>=8.0.0
Requires-Dist: lxml <6.0.0,>=5.0.0
Provides-Extra: dev
Requires-Dist: black ==24.10.0 ; extra == 'dev'
Requires-Dist: build ==1.2.2.post1 ; extra == 'dev'
Requires-Dist: isort ==5.13.2 ; extra == 'dev'
Requires-Dist: pre-commit ==4.0.1 ; extra == 'dev'
Requires-Dist: pylint ==3.3.1 ; extra == 'dev'
Requires-Dist: pytest ==8.3.3 ; extra == 'dev'
Requires-Dist: twine ==5.1.1 ; extra == 'dev'
